mshtensorflow/Activation.py
mshtensorflow/Dropout.py
mshtensorflow/Flatten.py
mshtensorflow/Layer.py
mshtensorflow/Loss_Function.py
mshtensorflow/Model.py
mshtensorflow/Optimizer.py
mshtensorflow/PCA.py
mshtensorflow/Read_and_process_data.py
mshtensorflow/Visualization.py
mshtensorflow/__init__.py
mshtensorflow/conv_layer.py
mshtensorflow/metrics.py
mshtensorflow/pool_layer.py
mshtensorflow/predicted_visualization.py
mshtensorflow/utilities.py
mshtensorflow-0.0.7.dist-info/LICENSE.txt
mshtensorflow-0.0.7.dist-info/METADATA
mshtensorflow-0.0.7.dist-info/WHEEL
mshtensorflow-0.0.7.dist-info/top_level.txt
mshtensorflow-0.0.7.dist-info/RECORD
